aiohttp_rpc/__init__.py
aiohttp_rpc/constants.py
aiohttp_rpc/decorators.py
aiohttp_rpc/errors.py
aiohttp_rpc/middlewares.py
aiohttp_rpc/py.typed
aiohttp_rpc/typedefs.py
aiohttp_rpc/utils.py
aiohttp_rpc/client/__init__.py
aiohttp_rpc/client/additional.py
aiohttp_rpc/client/base.py
aiohttp_rpc/client/http.py
aiohttp_rpc/client/websocket.py
aiohttp_rpc/protocol/__init__.py
aiohttp_rpc/protocol/method.py
aiohttp_rpc/protocol/request.py
aiohttp_rpc/protocol/response.py
aiohttp_rpc/server/__init__.py
aiohttp_rpc/server/base.py
aiohttp_rpc/server/http.py
aiohttp_rpc/server/utils.py
aiohttp_rpc/server/websocket.py
aiohttp_rpc-2.0.0.dist-info/licenses/LICENSE.txt
aiohttp_rpc-2.0.0.dist-info/METADATA
aiohttp_rpc-2.0.0.dist-info/WHEEL
aiohttp_rpc-2.0.0.dist-info/top_level.txt
aiohttp_rpc-2.0.0.dist-info/RECORD
