Metadata-Version: 2.4
Name: aiohttp-rpc
Version: 2.0.0
Summary: A simple JSON-RPC for aiohttp
Author-email: Michael Sulyak <michael@sulyak.info>
License: MIT
Project-URL: GitHub: issues, https://github.com/michael-sulyak/aiohttp-rpc/issues
Project-URL: GitHub: repo, https://github.com/michael-sulyak/aiohttp-rpc
Keywords: aiohttp,asyncio,json-rpc,rpc
Classifier: Development Status :: 4 - Beta
Classifier: Environment :: Web Environment
Classifier: Intended Audience :: Developers
Classifier: License :: OSI Approved :: MIT License
Classifier: Operating System :: OS Independent
Classifier: Programming Language :: Python
Classifier: Programming Language :: Python :: 3
Classifier: Programming Language :: Python :: 3.8
Classifier: Programming Language :: Python :: 3.9
Classifier: Programming Language :: Python :: 3.10
Classifier: Programming Language :: Python :: 3.11
Classifier: Programming Language :: Python :: 3.12
Classifier: Programming Language :: Python :: 3.13
Classifier: Framework :: AsyncIO
Classifier: Framework :: aiohttp
Classifier: Topic :: Internet
Classifier: Topic :: Communications
Classifier: Topic :: Software Development :: Libraries
Classifier: Topic :: Software Development :: Libraries :: Python Modules
Requires-Python: >=3.8
License-File: LICENSE.txt
Requires-Dist: aiohttp<4,>=3
Dynamic: license-file
